tmdbapis/__init__.py
tmdbapis/api3.py
tmdbapis/api4.py
tmdbapis/exceptions.py
tmdbapis/tmdb.py
tmdbapis/objs/__init__.py
tmdbapis/objs/base.py
tmdbapis/objs/image.py
tmdbapis/objs/mixin.py
tmdbapis/objs/pagination.py
tmdbapis/objs/reload.py
tmdbapis/objs/simple.py
tmdbapis-1.2.30.dist-info/licenses/LICENSE
tmdbapis-1.2.30.dist-info/METADATA
tmdbapis-1.2.30.dist-info/WHEEL
tmdbapis-1.2.30.dist-info/top_level.txt
tmdbapis-1.2.30.dist-info/RECORD
