Metadata-Version: 2.4
Name: tmdbapis
Version: 1.2.30
Summary: A lightweight Python library for The V3 and V4 TMDb APIs.
Home-page: https://github.com/Kometa-Team/TMDbAPIs
Author: Nathan Taggart
Author-email: kometateam@proton.me
License: MIT License
Project-URL: Documentation, https://tmdbapis.kometa.wiki
Project-URL: Funding, https://github.com/sponsors/meisnate12
Project-URL: Source, https://github.com/Kometa-Team/TMDbAPIs
Project-URL: Issues, https://github.com/Kometa-Team/TMDbAPIs/issues
Keywords: tmdbapis,tmdbapi,tmdb,wrapper,api
Classifier: Development Status :: 5 - Production/Stable
Classifier: Intended Audience :: Developers
Classifier: Topic :: Software Development :: Libraries
Classifier: Programming Language :: Python
Classifier: Programming Language :: Python :: 3.8
Classifier: Programming Language :: Python :: 3.9
Classifier: Programming Language :: Python :: 3.10
Classifier: Programming Language :: Python :: 3.11
Classifier: Programming Language :: Python :: 3.12
Requires-Python: >=3.8
License-File: LICENSE
Requires-Dist: requests
Requires-Dist: setuptools
Dynamic: author
Dynamic: author-email
Dynamic: classifier
Dynamic: description
Dynamic: home-page
Dynamic: keywords
Dynamic: license
Dynamic: license-file
Dynamic: project-url
Dynamic: requires-dist
Dynamic: requires-python
Dynamic: summary
